pyramid_listing/__init__.py
pyramid_listing/listing.py
pyramid_listing/pagination.py
pyramid_listing/resource.py
pyramid_listing-0.2.2.dist-info/LICENSE
pyramid_listing-0.2.2.dist-info/WHEEL
pyramid_listing-0.2.2.dist-info/METADATA
pyramid_listing-0.2.2.dist-info/RECORD
