Metadata-Version: 2.1
Name: pyramid_listing
Version: 0.2.2
Summary: Pyramid List Pagination contains helpers for pagination of result lists.
Home-page: https://github.com/holgi/pyramid_listing
License: Beerware
Keywords: pyramid list pagination resource
Author: Holger Frey
Author-email: mail@holgerfrey.de
Requires-Python: >=3.7
Classifier: Development Status :: 4 - Beta
Classifier: Intended Audience :: Developers
Classifier: Programming Language :: Python :: 3.7
Classifier: Programming Language :: Python :: 3.8
Classifier: Programming Language :: Python :: 3 :: Only
Classifier: License :: Freely Distributable
Classifier: Framework :: Pyramid
Requires-Dist: SQLAlchemy
Requires-Dist: black ; extra == "dev"
Requires-Dist: flake8 ; extra == "dev"
Requires-Dist: flake8-comprehensions ; extra == "dev"
Requires-Dist: isort ; extra == "dev"
Requires-Dist: keyring ; extra == "dev"
Requires-Dist: pre-commit ; extra == "dev"
Requires-Dist: Sphinx ; extra == "dev"
Requires-Dist: pytest >=4.0.0 ; extra == "test"
Requires-Dist: pytest-cov ; extra == "test"
Requires-Dist: pytest-mock ; extra == "test"
Requires-Dist: tox ; extra == "test"
Provides-Extra: dev
Provides-Extra: test
